qaoa_quimb/__init__.py
qaoa_quimb/circuit.py
qaoa_quimb/contraction.py
qaoa_quimb/decomp.py
qaoa_quimb/gates.py
qaoa_quimb/hamiltonian.py
qaoa_quimb/initialization.py
qaoa_quimb/launcher.py
qaoa_quimb/mps.py
qaoa_quimb/utils.py
qaoa_quimb-0.0.1.dist-info/METADATA
qaoa_quimb-0.0.1.dist-info/WHEEL
qaoa_quimb-0.0.1.dist-info/licenses/LICENSE
qaoa_quimb-0.0.1.dist-info/RECORD
