Metadata-Version: 2.1
Name: qaoa_quimb
Version: 0.0.1
Summary: A QAOA implementation in Quimb.
Project-URL: Homepage, https://github.com/juliendrapeau/qaoa-quimb
Author-email: Julien Drapeau <julien.drapeau@usherbrooke.ca>
License-File: LICENSE
Classifier: License :: OSI Approved :: MIT License
Classifier: Operating System :: OS Independent
Classifier: Programming Language :: Python :: 3
Requires-Python: >=3.7
